multidirectorycorpusreader/__init__.py
multidirectorycorpusreader/multidirectorycorpusreader.py
multidirectorycorpusreader-0.2.3.dist-info/LICENSE
multidirectorycorpusreader-0.2.3.dist-info/WHEEL
multidirectorycorpusreader-0.2.3.dist-info/METADATA
multidirectorycorpusreader-0.2.3.dist-info/RECORD
