Metadata-Version: 2.1
Name: multidirectorycorpusreader
Version: 0.2.3
Summary: 
Home-page: https://github.com/blackplague/multidirectorycorpusreader
License: LGPL-3.0
Author: Michael Andersen
Author-email: michael10andersen+mdcr@gmail.com
Requires-Python: >=3.7,<4.0
Classifier: License :: OSI Approved :: GNU Lesser General Public License v3 (LGPLv3)
Classifier: Programming Language :: Python :: 3
Classifier: Programming Language :: Python :: 3.10
Classifier: Programming Language :: Python :: 3.7
Classifier: Programming Language :: Python :: 3.8
Classifier: Programming Language :: Python :: 3.9
Project-URL: Bug Tracker, https://github.com/blackplague/multidirectorycorpusreader/issues
Project-URL: Repository, https://github.com/blackplague/multidirectorycorpusreader
